pyorc/enums.py
pyorc/predicates.py
pyorc/__init__.py
pyorc/reader.py
pyorc/typedescription.py
pyorc/_pyorc.cpython-310-darwin.so
pyorc/_pyorc.pyi
pyorc/py.typed
pyorc/writer.py
pyorc/converters.py
pyorc/errors.py
pyorc-0.10.0.dist-info/RECORD
pyorc-0.10.0.dist-info/LICENSE
pyorc-0.10.0.dist-info/WHEEL
pyorc-0.10.0.dist-info/top_level.txt
pyorc-0.10.0.dist-info/METADATA
