Metadata-Version: 2.2
Name: pyorc
Version: 0.10.0
Summary: Python module for reading and writing Apache ORC file format.
Home-page: https://github.com/noirello/pyorc
Author: noirello
Author-email: noirello@gmail.com
License: Apache License, Version 2.0
Keywords: python3,orc,apache-orc
Classifier: Development Status :: 3 - Alpha
Classifier: Intended Audience :: Developers
Classifier: Intended Audience :: System Administrators
Classifier: License :: OSI Approved :: Apache Software License
Classifier: Programming Language :: C++
Classifier: Programming Language :: Python :: 3 :: Only
Classifier: Programming Language :: Python :: 3.9
Classifier: Programming Language :: Python :: 3.10
Classifier: Programming Language :: Python :: 3.11
Classifier: Programming Language :: Python :: 3.12
Classifier: Programming Language :: Python :: 3.13
Requires-Python: >=3.6
License-File: LICENSE
Requires-Dist: tzdata>=2020.5; sys_platform == "win32"
Requires-Dist: backports.zoneinfo>=0.2.1; python_version < "3.9"
Dynamic: author
Dynamic: author-email
Dynamic: classifier
Dynamic: description
Dynamic: description-content-type
Dynamic: home-page
Dynamic: keywords
Dynamic: license
Dynamic: requires-dist
Dynamic: requires-python
Dynamic: summary
